rabbitmq_clients/__init__.py
rabbitmq_clients/core/__init__.py
rabbitmq_clients/core/base_connect.py
rabbitmq_clients/core/consumer.py
rabbitmq_clients/core/dto.py
rabbitmq_clients/core/exceptions.py
rabbitmq_clients/core/handlers.py
rabbitmq_clients/core/producer.py
rabbitmq_clients/core/types.py
rabbitmq_clients-0.1.22.dist-info/LICENSE
rabbitmq_clients-0.1.22.dist-info/METADATA
rabbitmq_clients-0.1.22.dist-info/WHEEL
rabbitmq_clients-0.1.22.dist-info/RECORD
