Metadata-Version: 2.3
Name: rabbitmq-clients
Version: 0.1.22
Summary: High level interfaces for work with RabbitMQ.
License: MIT
Author: deskent
Author-email: battenetciz@gmail.com
Requires-Python: >=3.10,<4.0
Classifier: License :: OSI Approved :: MIT License
Classifier: Programming Language :: Python :: 3
Classifier: Programming Language :: Python :: 3.10
Classifier: Programming Language :: Python :: 3.11
Classifier: Programming Language :: Python :: 3.12
Classifier: Programming Language :: Python :: 3.13
Requires-Dist: aio-pika (>=9.4.1,<10.0.0)
Project-URL: Repository, https://github.com/Deskent/rabbit_mq_client
